setup.py
Metric_Functions/Metric_Functions.py
Metric_Functions/__init__.py
Metric_Functions.egg-info/PKG-INFO
Metric_Functions.egg-info/SOURCES.txt
Metric_Functions.egg-info/dependency_links.txt
Metric_Functions.egg-info/not-zip-safe
Metric_Functions.egg-info/top_level.txt