Metadata-Version: 1.0
Name: Metric-Functions
Version: 1.0
Summary: Tulsa Public School distric data team data analysis functions
Home-page: UNKNOWN
Author: Charline LI
Author-email: lch129444@hotmail.com
License: UNKNOWN
Platform: UNKNOWN
